AUTHORS
LICENSE
MANIFEST.in
README.rst
setup.py
geventwebsocket/__init__.py
geventwebsocket/exceptions.py
geventwebsocket/handler.py
geventwebsocket/logging.py
geventwebsocket/resource.py
geventwebsocket/server.py
geventwebsocket/utf8validator.py
geventwebsocket/utils.py
geventwebsocket/websocket.py
geventwebsocket/gunicorn/__init__.py
geventwebsocket/gunicorn/workers.py
geventwebsocket/protocols/__init__.py
geventwebsocket/protocols/base.py
geventwebsocket/protocols/wamp.py
prat_geventwebsocket.egg-info/PKG-INFO
prat_geventwebsocket.egg-info/SOURCES.txt
prat_geventwebsocket.egg-info/dependency_links.txt
prat_geventwebsocket.egg-info/not-zip-safe
prat_geventwebsocket.egg-info/requires.txt
prat_geventwebsocket.egg-info/top_level.txt