Metadata-Version: 1.1
Name: prat-geventwebsocket
Version: 0.9.5
Summary: Websocket handler for the gevent pywsgi server, a Python network library
Home-page: https://bitbucket.org/Jeffrey/gevent-websocket
Author: Jeffrey Gelens
Author-email: jeffrey@noppo.pro
License:    Copyright 2011-2013 Jeffrey Gelens <jeffrey@noppo.pro>
